cg_hermes/__init__.py
cg_hermes/__main__.py
cg_hermes/cli/__init__.py
cg_hermes/cli/base.py
cg_hermes/cli/common.py
cg_hermes/cli/convert.py
cg_hermes/cli/export.py
cg_hermes/cli/validate.py
cg_hermes/config/balsamic.py
cg_hermes/config/balsamic_umi.py
cg_hermes/config/fluffy.py
cg_hermes/config/microsalt.py
cg_hermes/config/mip_dna.py
cg_hermes/config/mip_rna.py
cg_hermes/config/mutant.py
cg_hermes/config/nallo.py
cg_hermes/config/nextflow.py
cg_hermes/config/raredisease.py
cg_hermes/config/rnafusion.py
cg_hermes/config/taxprofiler.py
cg_hermes/config/tomte.py
cg_hermes/constants/hermes.py
cg_hermes/constants/tags.py
cg_hermes/constants/workflow.py
cg_hermes/deliverables.py
cg_hermes/exceptions.py
cg_hermes/models/__init__.py
cg_hermes/models/tags.py
cg_hermes/models/workflow_deliverables.py
cg_hermes/validate.py
cg_hermes-6.1.7.dist-info/METADATA
cg_hermes-6.1.7.dist-info/WHEEL
cg_hermes-6.1.7.dist-info/entry_points.txt
cg_hermes-6.1.7.dist-info/RECORD
