Metadata-Version: 2.1
Name: cg-hermes
Version: 6.1.7
Summary: Convert information between pipelines and CG
Author: Måns Magnusson
Author-email: mans.magnusson@scilifelab.se
Requires-Python: >=3.12,<4.0
Classifier: Programming Language :: Python :: 3
Requires-Dist: bump2version
Requires-Dist: coloredlogs
Requires-Dist: pydantic (>=2.0.0,<3.0.0)
Requires-Dist: pyyaml
Requires-Dist: tabulate
Requires-Dist: typer
Requires-Dist: typing-extensions
